worker_automate_hub/__init__.py
worker_automate_hub/api/__init__.py
worker_automate_hub/api/ahead_service.py
worker_automate_hub/api/client.py
worker_automate_hub/api/datalake_service.py
worker_automate_hub/api/helpers/__init__.py
worker_automate_hub/api/helpers/api_helpers.py
worker_automate_hub/api/rdp_service.py
worker_automate_hub/api/rpa_fila_service.py
worker_automate_hub/api/rpa_historico_service.py
worker_automate_hub/api/webhook_service.py
worker_automate_hub/cli.py
worker_automate_hub/config/__init__.py
worker_automate_hub/config/settings.py
worker_automate_hub/config.py
worker_automate_hub/core/so_manipulation.py
worker_automate_hub/decorators/__init__.py
worker_automate_hub/decorators/deprecation.py
worker_automate_hub/decorators/rate_limit.py
worker_automate_hub/decorators/repeat.py
worker_automate_hub/decorators/retry.py
worker_automate_hub/decorators/singleton.py
worker_automate_hub/decorators/timeit.py
worker_automate_hub/models/__init__.py
worker_automate_hub/models/dao/__init__.py
worker_automate_hub/models/dao/rpa_configuracao.py
worker_automate_hub/models/dao/rpa_fila.py
worker_automate_hub/models/dao/rpa_historico.py
worker_automate_hub/models/dao/rpa_processo.py
worker_automate_hub/models/dao/rpa_robo.py
worker_automate_hub/models/dto/__init__.py
worker_automate_hub/models/dto/rpa_historico_request_dto.py
worker_automate_hub/models/dto/rpa_processo_entrada_dto.py
worker_automate_hub/models/dto/rpa_processo_rdp_dto.py
worker_automate_hub/models/dto/rpa_sap_dto.py
worker_automate_hub/models/dto/rpa_sistema_dto.py
worker_automate_hub/tasks/__init__.py
worker_automate_hub/tasks/jobs/__init__.py
worker_automate_hub/tasks/jobs/abertura_livros_fiscais.py
worker_automate_hub/tasks/jobs/coleta_dje_process.py
worker_automate_hub/tasks/jobs/coleta_envio_ftp.py
worker_automate_hub/tasks/jobs/conexao_rdp.py
worker_automate_hub/tasks/jobs/cte_manual.py
worker_automate_hub/tasks/jobs/cte_xml.py
worker_automate_hub/tasks/jobs/descartes.py
worker_automate_hub-0.5.997.dist-info/entry_points.txt
worker_automate_hub-0.5.997.dist-info/METADATA
worker_automate_hub-0.5.997.dist-info/WHEEL
worker_automate_hub-0.5.997.dist-info/RECORD
